MANIFEST.in
README.md
setup.cfg
setup.py
chainer_openpose/__init__.py
chainer_openpose/pose_detector.py
chainer_openpose.egg-info/PKG-INFO
chainer_openpose.egg-info/SOURCES.txt
chainer_openpose.egg-info/dependency_links.txt
chainer_openpose.egg-info/not-zip-safe
chainer_openpose.egg-info/requires.txt
chainer_openpose.egg-info/top_level.txt
chainer_openpose/datasets/__init__.py
chainer_openpose/datasets/download.py
chainer_openpose/datasets/coco/__init__.py
chainer_openpose/datasets/coco/coco_dataset.py
chainer_openpose/datasets/coco/coco_utils.py
chainer_openpose/datasets/fashion_landmark/__init__.py
chainer_openpose/datasets/fashion_landmark/fashion_landmark_keypoints_dataset.py
chainer_openpose/datasets/fashion_landmark/fashion_landmark_utils.py
chainer_openpose/extensions/__init__.py
chainer_openpose/extensions/openpose_vis_report.py
chainer_openpose/links/__init__.py
chainer_openpose/links/model/__init__.py
chainer_openpose/links/model/openpose/__init__.py
chainer_openpose/links/model/openpose/openpose.py
chainer_openpose/links/model/openpose/openpose_train_chain.py
chainer_openpose/transforms/__init__.py
chainer_openpose/transforms/box.py
chainer_openpose/transforms/distort_color.py
chainer_openpose/transforms/domain_randomize.py
chainer_openpose/transforms/flip.py
chainer_openpose/transforms/heatmap.py
chainer_openpose/transforms/paf.py
chainer_openpose/transforms/random_crop.py
chainer_openpose/transforms/random_erase.py
chainer_openpose/transforms/random_flip.py
chainer_openpose/transforms/random_resize.py
chainer_openpose/transforms/random_rotate.py
chainer_openpose/transforms/resize.py
chainer_openpose/visualizations/__init__.py
chainer_openpose/visualizations/overlay.py